{
  "bg": 177, 
  "temp": "absolute", 
  "snoozeBG": 175, 
  "timestamp": "2016-04-27T22:36:22.316109", 
  "missing": [
    "duration", 
    "rate"
  ], 
  "reason": "max_iob 1, adj. req. rate:1.6 to maxSafeBasal:0.8, temp 0.8 >~ req 0.8U/hr", 
  "eventualBG": 175, 
  "error": "missing required input fields", 
  "input": {
    "reason": "max_iob 1, adj. req. rate:1.6 to maxSafeBasal:0.8, temp 0.8 >~ req 0.8U/hr", 
    "bg": 177, 
    "eventualBG": 175, 
    "temp": "absolute", 
    "snoozeBG": 175, 
    "tick": "+1"
  }, 
  "tick": "+1"
}