[
  {
    "trend_arrow": "45_UP", 
    "system_time": "2016-05-06T02:25:36", 
    "display_time": "2016-05-07T19:26:31", 
    "glucose": 145
  }, 
  {
    "trend_arrow": "FLAT", 
    "system_time": "2016-05-06T02:20:36", 
    "display_time": "2016-05-07T19:21:31", 
    "glucose": 130
  }, 
  {
    "trend_arrow": "FLAT", 
    "system_time": "2016-05-06T02:15:36", 
    "display_time": "2016-05-07T19:16:31", 
    "glucose": 123
  }, 
  {
    "trend_arrow": "FLAT", 
    "system_time": "2016-05-06T02:10:37", 
    "display_time": "2016-05-07T19:11:31", 
    "glucose": 122
  }, 
  {
    "trend_arrow": "FLAT", 
    "system_time": "2016-05-06T02:05:37", 
    "display_time": "2016-05-07T19:06:31", 
    "glucose": 121
  }
]