[
  {
    "trend_arrow": "FLAT", 
    "system_time": "2016-05-04T08:30:45", 
    "display_time": "2016-05-06T01:31:40", 
    "glucose": 188
  }, 
  {
    "trend_arrow": "FLAT", 
    "system_time": "2016-05-04T08:25:45", 
    "display_time": "2016-05-06T01:26:40", 
    "glucose": 186
  }, 
  {
    "trend_arrow": "FLAT", 
    "system_time": "2016-05-04T08:20:45", 
    "display_time": "2016-05-06T01:21:40", 
    "glucose": 184
  }, 
  {
    "trend_arrow": "FLAT", 
    "system_time": "2016-05-04T08:15:45", 
    "display_time": "2016-05-06T01:16:40", 
    "glucose": 182
  }, 
  {
    "trend_arrow": "FLAT", 
    "system_time": "2016-05-04T08:10:45", 
    "display_time": "2016-05-06T01:11:40", 
    "glucose": 176
  }
]