[
  {
    "trend_arrow": "DOUBLE_UP", 
    "system_time": "2016-05-09T03:35:22", 
    "display_time": "2016-05-10T20:36:17", 
    "glucose": 199
  }, 
  {
    "trend_arrow": "DOUBLE_UP", 
    "system_time": "2016-05-09T03:30:22", 
    "display_time": "2016-05-10T20:31:17", 
    "glucose": 184
  }, 
  {
    "trend_arrow": "DOUBLE_UP", 
    "system_time": "2016-05-09T03:25:22", 
    "display_time": "2016-05-10T20:26:17", 
    "glucose": 164
  }, 
  {
    "trend_arrow": "SINGLE_UP", 
    "system_time": "2016-05-09T03:20:22", 
    "display_time": "2016-05-10T20:21:17", 
    "glucose": 142
  }, 
  {
    "trend_arrow": "FLAT", 
    "system_time": "2016-05-09T03:15:22", 
    "display_time": "2016-05-10T20:16:17", 
    "glucose": 123
  }
]