[
  {
    "trend_arrow": "FLAT", 
    "system_time": "2016-05-03T13:35:49", 
    "display_time": "2016-05-05T06:36:43", 
    "glucose": 150
  }, 
  {
    "trend_arrow": "FLAT", 
    "system_time": "2016-05-03T13:30:49", 
    "display_time": "2016-05-05T06:31:43", 
    "glucose": 148
  }, 
  {
    "trend_arrow": "FLAT", 
    "system_time": "2016-05-03T13:25:49", 
    "display_time": "2016-05-05T06:26:43", 
    "glucose": 148
  }, 
  {
    "trend_arrow": "FLAT", 
    "system_time": "2016-05-03T13:20:49", 
    "display_time": "2016-05-05T06:21:43", 
    "glucose": 147
  }, 
  {
    "trend_arrow": "FLAT", 
    "system_time": "2016-05-03T13:15:49", 
    "display_time": "2016-05-05T06:16:43", 
    "glucose": 144
  }
]