[
  {
    "trend_arrow": "FLAT", 
    "system_time": "2016-04-25T11:47:11", 
    "display_time": "2016-04-27T04:48:06", 
    "glucose": 121
  }, 
  {
    "trend_arrow": "FLAT", 
    "system_time": "2016-04-25T11:42:11", 
    "display_time": "2016-04-27T04:43:06", 
    "glucose": 122
  }, 
  {
    "trend_arrow": "FLAT", 
    "system_time": "2016-04-25T11:37:11", 
    "display_time": "2016-04-27T04:38:06", 
    "glucose": 120
  }, 
  {
    "trend_arrow": "FLAT", 
    "system_time": "2016-04-25T11:32:11", 
    "display_time": "2016-04-27T04:33:06", 
    "glucose": 116
  }, 
  {
    "trend_arrow": "FLAT", 
    "system_time": "2016-04-25T11:27:11", 
    "display_time": "2016-04-27T04:28:06", 
    "glucose": 116
  }
]