[
  {
    "trend_arrow": "FLAT", 
    "system_time": "2016-06-24T13:11:48", 
    "display_time": "2016-06-26T06:11:41", 
    "glucose": 99
  }, 
  {
    "trend_arrow": "FLAT", 
    "system_time": "2016-06-24T13:06:48", 
    "display_time": "2016-06-26T06:06:41", 
    "glucose": 101
  }, 
  {
    "trend_arrow": "FLAT", 
    "system_time": "2016-06-24T13:01:48", 
    "display_time": "2016-06-26T06:01:41", 
    "glucose": 98
  }, 
  {
    "trend_arrow": "FLAT", 
    "system_time": "2016-06-24T12:56:48", 
    "display_time": "2016-06-26T05:56:41", 
    "glucose": 104
  }, 
  {
    "trend_arrow": "FLAT", 
    "system_time": "2016-06-24T12:51:48", 
    "display_time": "2016-06-26T05:51:41", 
    "glucose": 93
  }
]