{
  "pump": {
    "battery": {
      "status": "normal", 
      "voltage": 1.56
    }, 
    "status": {
      "status": "normal", 
      "timestamp": "2016-06-18T04:56:15.000Z", 
      "bolusing": false, 
      "suspended": false
    }, 
    "reservoir": 182.2, 
    "clock": "2016-06-17T23:55:37-05:00"
  }, 
  "openaps": {
    "suggested": {
      "bg": 120, 
      "temp": "absolute", 
      "snoozeBG": 112, 
      "timestamp": "2016-06-18T04:56:25.000Z", 
      "rate": 0.5, 
      "reason": "Eventual BG 112>110, no temp, setting 0.49U/hr", 
      "eventualBG": 112, 
      "duration": 30, 
      "tick": "+1"
    }, 
    "iob": {
      "timestamp": "2016-06-18T04:56:19.000Z", 
      "activity": 0.0021235362433862435, 
      "iob": 0.1539174502157552, 
      "bolusiob": 0
    }, 
    "enacted": {
      "bg": 120, 
      "temp": "absolute", 
      "snoozeBG": 112, 
      "recieved": true, 
      "reason": "Eventual BG 112>110, no temp, setting 0.49U/hr", 
      "rate": 0.5, 
      "eventualBG": 112, 
      "timestamp": "2016-06-18T04:56:30.000Z", 
      "duration": 30, 
      "tick": "+1"
    }
  }
}