{
  "pump": {
    "battery": {
      "status": "normal", 
      "voltage": 1.48
    }, 
    "status": {
      "status": "normal", 
      "timestamp": "2016-04-28T04:26:04.000Z", 
      "bolusing": false, 
      "suspended": false
    }, 
    "reservoir": 184.5, 
    "clock": "2016-04-27T23:25:10-05:00"
  }, 
  "openaps": {
    "suggested": {
      "bg": 196, 
      "temp": "absolute", 
      "snoozeBG": 171, 
      "timestamp": "2016-04-28T04:26:13.000Z", 
      "reason": "max_iob 1, adj. req. rate:1.1 to maxSafeBasal:0.8, temp 0.8 >~ req 0.8U/hr", 
      "eventualBG": 171, 
      "tick": "+2"
    }, 
    "iob": {
      "timestamp": "2016-04-28T04:26:08.000Z", 
      "activity": 0.004891842857142857, 
      "iob": 0.551971045235567, 
      "bolusiob": 0
    }, 
    "enacted": {
      "bg": 196, 
      "temp": "absolute", 
      "missing": [
        "duration", 
        "rate"
      ], 
      "timestamp": "2016-04-28T04:26:16.000Z", 
      "snoozeBG": 171, 
      "reason": "max_iob 1, adj. req. rate:1.1 to maxSafeBasal:0.8, temp 0.8 >~ req 0.8U/hr", 
      "eventualBG": 171, 
      "error": "missing required input fields", 
      "input": {
        "bg": 196, 
        "temp": "absolute", 
        "snoozeBG": 171, 
        "reason": "max_iob 1, adj. req. rate:1.1 to maxSafeBasal:0.8, temp 0.8 >~ req 0.8U/hr", 
        "eventualBG": 171, 
        "tick": "+2"
      }, 
      "tick": "+2"
    }
  }
}