{
  "pump": {
    "battery": {
      "status": "normal", 
      "voltage": 1.57
    }, 
    "status": {
      "status": "normal", 
      "timestamp": "2016-05-09T10:51:07.000Z", 
      "bolusing": false, 
      "suspended": false
    }, 
    "reservoir": 190.3, 
    "clock": "2016-05-09T05:50:13-05:00"
  }, 
  "openaps": {
    "suggested": {
      "bg": 131, 
      "temp": "absolute", 
      "snoozeBG": 122, 
      "timestamp": "2016-05-09T10:51:16.000Z", 
      "reason": "Eventual BG 122>115, temp 0.85 >~ req 0.836U/hr", 
      "eventualBG": 122, 
      "tick": "+1"
    }, 
    "iob": {
      "timestamp": "2016-05-09T10:51:11.000Z", 
      "activity": 0.0044398588183421515, 
      "iob": 0.22640964641097266, 
      "bolusiob": 0
    }, 
    "enacted": {
      "bg": 131, 
      "temp": "absolute", 
      "missing": [
        "duration", 
        "rate"
      ], 
      "timestamp": "2016-05-09T10:51:20.000Z", 
      "snoozeBG": 122, 
      "reason": "Eventual BG 122>115, temp 0.85 >~ req 0.836U/hr", 
      "eventualBG": 122, 
      "error": "missing required input fields", 
      "input": {
        "bg": 131, 
        "temp": "absolute", 
        "snoozeBG": 122, 
        "reason": "Eventual BG 122>115, temp 0.85 >~ req 0.836U/hr", 
        "eventualBG": 122, 
        "tick": "+1"
      }, 
      "tick": "+1"
    }
  }
}