{
  "pump": {
    "battery": {
      "status": "normal", 
      "voltage": 1.35
    }, 
    "status": {
      "status": "normal", 
      "timestamp": "2016-07-03T10:16:14.000Z", 
      "bolusing": false, 
      "suspended": false
    }, 
    "reservoir": 79.7, 
    "clock": "2016-07-03T05:15:39-05:00"
  }, 
  "openaps": {
    "suggested": {
      "bg": 176, 
      "temp": "absolute", 
      "snoozeBG": 148, 
      "timestamp": "2016-07-03T10:16:24.000Z", 
      "reason": "Eventual BG 148>105, adj. req. rate:1.8 to maxSafeBasal:1.4, temp 1.35 >~ req 1.35U/hr", 
      "eventualBG": 148, 
      "tick": "+1"
    }, 
    "iob": {
      "timestamp": "2016-07-03T10:16:19.000Z", 
      "activity": 0.010240467283950616, 
      "iob": 0.6368076781954071, 
      "bolusiob": 0
    }, 
    "enacted": {
      "bg": 176, 
      "temp": "absolute", 
      "missing": [
        "duration", 
        "rate"
      ], 
      "timestamp": "2016-07-03T10:16:29.000Z", 
      "snoozeBG": 148, 
      "reason": "Eventual BG 148>105, adj. req. rate:1.8 to maxSafeBasal:1.4, temp 1.35 >~ req 1.35U/hr", 
      "eventualBG": 148, 
      "error": "missing required input fields", 
      "input": {
        "bg": 176, 
        "temp": "absolute", 
        "snoozeBG": 148, 
        "reason": "Eventual BG 148>105, adj. req. rate:1.8 to maxSafeBasal:1.4, temp 1.35 >~ req 1.35U/hr", 
        "eventualBG": 148, 
        "tick": "+1"
      }, 
      "tick": "+1"
    }
  }
}