{
  "pump": {
    "battery": {
      "status": "normal", 
      "voltage": 1.57
    }, 
    "status": {
      "status": "normal", 
      "timestamp": "2016-05-13T00:26:02.000Z", 
      "bolusing": false, 
      "suspended": false
    }, 
    "reservoir": 85.3, 
    "clock": "2016-05-12T19:25:12-05:00"
  }, 
  "openaps": {
    "suggested": {
      "bg": 139, 
      "temp": "absolute", 
      "snoozeBG": 161, 
      "timestamp": "2016-05-13T00:26:12.000Z", 
      "reason": "Eventual BG 62<95bolus snooze: eventual BG range 62-161", 
      "eventualBG": 62, 
      "tick": -7
    }, 
    "iob": {
      "timestamp": "2016-05-13T00:26:06.000Z", 
      "activity": 0.009007601410934743, 
      "iob": 1.4456210029905556, 
      "bolusiob": 0.9434693253688888
    }, 
    "enacted": {
      "bg": 139, 
      "temp": "absolute", 
      "missing": [
        "duration", 
        "rate"
      ], 
      "timestamp": "2016-05-13T00:26:15.000Z", 
      "snoozeBG": 161, 
      "reason": "Eventual BG 62<95bolus snooze: eventual BG range 62-161", 
      "eventualBG": 62, 
      "error": "missing required input fields", 
      "input": {
        "bg": 139, 
        "temp": "absolute", 
        "snoozeBG": 161, 
        "reason": "Eventual BG 62<95bolus snooze: eventual BG range 62-161", 
        "eventualBG": 62, 
        "tick": -7
      }, 
      "tick": -7
    }
  }
}