{
  "pump": {
    "battery": {
      "status": "normal", 
      "voltage": 1.56
    }, 
    "status": {
      "status": "normal", 
      "timestamp": "2016-05-10T10:06:01.000Z", 
      "bolusing": false, 
      "suspended": false
    }, 
    "reservoir": 162.8, 
    "clock": "2016-05-10T05:05:11-05:00"
  }, 
  "openaps": {
    "suggested": {
      "bg": 139, 
      "temp": "absolute", 
      "snoozeBG": 129, 
      "timestamp": "2016-05-10T10:06:10.000Z", 
      "rate": 0, 
      "reason": "Eventual BG 129>95 but Delta -2 < Exp. Delta -1.9; cancel", 
      "eventualBG": 129, 
      "duration": 0, 
      "tick": -2
    }, 
    "iob": {
      "timestamp": "2016-05-10T10:06:05.000Z", 
      "activity": 0.003669347442680775, 
      "iob": 0.25178946976805555, 
      "bolusiob": 0
    }, 
    "enacted": {
      "bg": 139, 
      "temp": "absolute", 
      "snoozeBG": 129, 
      "recieved": true, 
      "reason": "Eventual BG 129>95 but Delta -2 < Exp. Delta -1.9; cancel", 
      "rate": 0, 
      "eventualBG": 129, 
      "timestamp": "2016-05-10T10:06:15.000Z", 
      "duration": 0, 
      "tick": -2
    }
  }
}