{
  "pump": {
    "battery": {
      "status": "normal", 
      "voltage": 1.55
    }, 
    "status": {
      "status": "normal", 
      "timestamp": "2016-05-15T05:16:02.000Z", 
      "bolusing": false, 
      "suspended": false
    }, 
    "reservoir": 37.5, 
    "clock": "2016-05-15T00:15:12-05:00"
  }, 
  "openaps": {
    "suggested": {
      "bg": 235, 
      "temp": "absolute", 
      "snoozeBG": 231, 
      "timestamp": "2016-05-15T05:16:11.000Z", 
      "reason": "Eventual BG 67<95bolus snooze: eventual BG range 67-231", 
      "eventualBG": 67, 
      "tick": -1
    }, 
    "iob": {
      "timestamp": "2016-05-15T05:16:06.000Z", 
      "activity": 0.011151111111111108, 
      "iob": 2.4660298826533333, 
      "bolusiob": 1.5614896614400002
    }, 
    "enacted": {
      "bg": 235, 
      "temp": "absolute", 
      "missing": [
        "duration", 
        "rate"
      ], 
      "timestamp": "2016-05-15T05:16:14.000Z", 
      "snoozeBG": 231, 
      "reason": "Eventual BG 67<95bolus snooze: eventual BG range 67-231", 
      "eventualBG": 67, 
      "error": "missing required input fields", 
      "input": {
        "bg": 235, 
        "temp": "absolute", 
        "snoozeBG": 231, 
        "reason": "Eventual BG 67<95bolus snooze: eventual BG range 67-231", 
        "eventualBG": 67, 
        "tick": -1
      }, 
      "tick": -1
    }
  }
}